odoo8_addon_mail_print-8.0.1.0.0.99.dev16-py3.8-nspkg.pth
odoo_addons/mail_print/README.rst
odoo_addons/mail_print/__init__.py
odoo_addons/mail_print/__openerp__.py
odoo_addons/mail_print/report.xml
odoo_addons/mail_print/i18n/ca.po
odoo_addons/mail_print/i18n/de.po
odoo_addons/mail_print/i18n/el_GR.po
odoo_addons/mail_print/i18n/es.po
odoo_addons/mail_print/i18n/es_CO.po
odoo_addons/mail_print/i18n/fi.po
odoo_addons/mail_print/i18n/fr.po
odoo_addons/mail_print/i18n/it.po
odoo_addons/mail_print/i18n/mail_print.pot
odoo_addons/mail_print/i18n/nb.po
odoo_addons/mail_print/i18n/pt_BR.po
odoo_addons/mail_print/i18n/ru.po
odoo_addons/mail_print/i18n/sl.po
odoo_addons/mail_print/i18n/sv.po
odoo_addons/mail_print/i18n/tr.po
odoo_addons/mail_print/static/description/icon.png
odoo_addons/mail_print/static/src/css/mail.css
odoo_addons/mail_print/static/src/js/mail.js
odoo_addons/mail_print/static/src/xml/mail.xml
odoo_addons/mail_print/views/mail_message_report.xml
odoo_addons/mail_print/views/templates.xml
odoo8_addon_mail_print-8.0.1.0.0.99.dev16.dist-info/METADATA
odoo8_addon_mail_print-8.0.1.0.0.99.dev16.dist-info/WHEEL
odoo8_addon_mail_print-8.0.1.0.0.99.dev16.dist-info/namespace_packages.txt
odoo8_addon_mail_print-8.0.1.0.0.99.dev16.dist-info/top_level.txt
odoo8_addon_mail_print-8.0.1.0.0.99.dev16.dist-info/RECORD
